[
  {
    "arb":"",
    "ban":"",
    "eng":"1. Nun. By the pen and what they inscribe,"
  },
  {
    "arb":"",
    "ban":"",
    "eng":"2. You are not, [O Muhammad], by the favor of your Lord, a madman."
  },
  {
    "arb":"",
    "ban":"",
    "eng":"3. And indeed, for you is a reward uninterrupted."
  },
  {
    "arb":"",
    "ban":"",
    "eng":"4. And indeed, you are of a great moral character."
  },
  {
    "arb":"",
    "ban":"",
    "eng":"5. So you will see and they will see"
  },
  {
    "arb":"",
    "ban":"",
    "eng":"6. Which of you is the afflicted [by a devil]."
  },
  {
    "arb":"",
    "ban":"",
    "eng":"7. Indeed, your Lord is most knowing of who has gone astray from His way, and He is most knowing of the [rightly] guided."
  },
  {
    "arb":"",
    "ban":"",
    "eng":"8. Then do not obey the deniers."
  },
  {
    "arb":"",
    "ban":"",
    "eng":"9. They wish that you would soften [in your position], so they would soften [toward you]."
  },
  {
    "arb":"",
    "ban":"",
    "eng":"10. And do not obey every worthless habitual swearer"
  },
  {
    "arb":"",
    "ban":"",
    "eng":"11. [And] scorner, going about with malicious gossip -"
  },
  {
    "arb":"",
    "ban":"",
    "eng":"12. A preventer of good, transgressing and sinful,"
  },
  {
    "arb":"",
    "ban":"",
    "eng":"13. Cruel, moreover, and an illegitimate pretender."
  },
  {
    "arb":"",
    "ban":"",
    "eng":"14. Because he is a possessor of wealth and children,"
  },
  {
    "arb":"",
    "ban":"",
    "eng":"15. When Our verses are recited to him, he says, 'Legends of the former peoples.'"
  },
  {
    "arb":"",
    "ban":"",
    "eng":"16. We will brand him upon the snout."
  },
  {
    "arb":"",
    "ban":"",
    "eng":"17. Indeed, We have tried them as We tried the companions of the garden, when they swore to cut its fruit in the [early] morning"
  },
  {
    "arb":"",
    "ban":"",
    "eng":"18. Without making exception."
  },
  {
    "arb":"",
    "ban":"",
    "eng":"19. So there came upon the garden an affliction from your Lord while they were asleep."
  },
  {
    "arb":"",
    "ban":"",
    "eng":"20. And it became as though reaped."
  },
  {
    "arb":"",
    "ban":"",
    "eng":"21. And they called one another at morning,"
  },
  {
    "arb":"",
    "ban":"",
    "eng":"22. [Saying], 'Go early to your crop if you would cut the fruit.'"
  },
  {
    "arb":"",
    "ban":"",
    "eng":"23. So they set out, while lowering their voices,"
  },
  {
    "arb":"",
    "ban":"",
    "eng":"24. [Saying], 'There will surely not enter it today upon you [any] poor person.'"
  },
  {
    "arb":"",
    "ban":"",
    "eng":"25. And they went early in determination, [assuming themselves] able."
  },
  {
    "arb":"",
    "ban":"",
    "eng":"26. But when they saw it, they said, 'Indeed, we are lost;"
  },
  {
    "arb":"",
    "ban":"",
    "eng":"27. Rather, we have been deprived.'"
  },
  {
    "arb":"",
    "ban":"",
    "eng":"28. The most moderate of them said, 'Did I not say to you, 'Why do you not exalt [Allah]?' '"
  },
  {
    "arb":"",
    "ban":"",
    "eng":"29. They said, 'Exalted is our Lord! Indeed, we were wrongdoers.'"
  },
  {
    "arb":"",
    "ban":"",
    "eng":"30. Then they approached one another, blaming each other."
  },
  {
    "arb":"",
    "ban":"",
    "eng":"31. They said, 'O woe to us; indeed we were transgressors."
  },
  {
    "arb":"",
    "ban":"",
    "eng":"32. Perhaps our Lord will substitute for us [one] better than it. Indeed, we are toward our Lord desirous.'"
  },
  {
    "arb":"",
    "ban":"",
    "eng":"33. Such is the punishment [of this world]. And the punishment of the Hereafter is greater, if they only knew."
  },
  {
    "arb":"",
    "ban":"",
    "eng":"34. Indeed, for the righteous with their Lord are the Gardens of Pleasure."
  },
  {
    "arb":"",
    "ban":"",
    "eng":"35. Then will We treat the Muslims like the criminals?"
  },
  {
    "arb":"",
    "ban":"",
    "eng":"36. What is [the matter] with you? How do you judge?"
  },
  {
    "arb":"",
    "ban":"",
    "eng":"37. Or do you have a scripture in which you learn"
  },
  {
    "arb":"",
    "ban":"",
    "eng":"38. That indeed for you is whatever you choose?"
  },
  {
    "arb":"",
    "ban":"",
    "eng":"39. Or do you have oaths [binding] upon Us, extending until the Day of Resurrection, that indeed for you is whatever you judge?"
  },
  {
    "arb":"",
    "ban":"",
    "eng":"40. Ask them which of them, for that [claim], is responsible."
  },
  {
    "arb":"",
    "ban":"",
    "eng":"41. Or do they have partners? Then let them bring their partners, if they should be truthful."
  },
  {
    "arb":"",
    "ban":"",
    "eng":"42. The Day the shin will be uncovered and they are invited to prostration but the disbelievers will not be able,"
  },
  {
    "arb":"",
    "ban":"",
    "eng":"43. Their eyes humbled, humiliation will cover them. And they used to be invited to prostration while they were sound."
  },
  {
    "arb":"",
    "ban":"",
    "eng":"44. So leave Me, [O Muhammad], with [the matter of] whoever denies the Qur'an. We will progressively lead them [to punishment] from where they do not know."
  },
  {
    "arb":"",
    "ban":"",
    "eng":"45. And I will give them time. Indeed, My plan is firm."
  },
  {
    "arb":"",
    "ban":"",
    "eng":"46. Or do you ask of them a payment, so they are by debt burdened down?"
  },
  {
    "arb":"",
    "ban":"",
    "eng":"47. Or have they [knowledge of] the unseen, so they write [it] down?"
  },
  {
    "arb":"",
    "ban":"",
    "eng":"48. Then be patient for the decision of your Lord, [O Muhammad], and be not like the companion of the fish when he called out while he was distressed."
  },
  {
    "arb":"",
    "ban":"",
    "eng":"49. If not that a favor from his Lord overtook him, he would have been thrown onto the naked shore while he was censured."
  },
  {
    "arb":"",
    "ban":"",
    "eng":"50. And his Lord chose him and made him of the righteous."
  },
  {
    "arb":"",
    "ban":"",
    "eng":"51. And indeed, those who disbelieve would almost make you slip with their eyes when they hear the message, and they say, 'Indeed, he is mad.'"
  },
  {
    "arb":"",
    "ban":"",
    "eng":"52. But it is not except a reminder to the worlds."
  }
]
