[
  {
    "arb":"",
    "ban":"",
    "eng":"1. By those [angels] who extract with violence"
  },
  {
    "arb":"",
    "ban":"",
    "eng":"2. And [by] those who remove with ease"
  },
  {
    "arb":"",
    "ban":"",
    "eng":"3. And [by] those who glide [as if] swimming"
  },
  {
    "arb":"",
    "ban":"",
    "eng":"4. And those who race each other in a race"
  },
  {
    "arb":"",
    "ban":"",
    "eng":"5. And those who arrange [each] matter,"
  },
  {
    "arb":"",
    "ban":"",
    "eng":"6. On the Day the blast [of the Horn] will convulse [creation],"
  },
  {
    "arb":"",
    "ban":"",
    "eng":"7. There will follow it the subsequent [one]."
  },
  {
    "arb":"",
    "ban":"",
    "eng":"8. Hearts, that Day, will tremble,"
  },
  {
    "arb":"",
    "ban":"",
    "eng":"9. Their eyes humbled."
  },
  {
    "arb":"",
    "ban":"",
    "eng":"10. They are [presently] saying, 'Will we indeed be returned to [our] former state [of life]?"
  },
  {
    "arb":"",
    "ban":"",
    "eng":"11. Even if we should be decayed bones?"
  },
  {
    "arb":"",
    "ban":"",
    "eng":"12. They say, 'That, then, would be a losing return.'"
  },
  {
    "arb":"",
    "ban":"",
    "eng":"13. Indeed, it will be but one shout,"
  },
  {
    "arb":"",
    "ban":"",
    "eng":"14. And suddenly they will be [alert] upon the earth's surface."
  },
  {
    "arb":"",
    "ban":"",
    "eng":"15. Has there reached you the story of Moses? -"
  },
  {
    "arb":"",
    "ban":"",
    "eng":"16. When his Lord called to him in the sacred valley of Tuwa,"
  },
  {
    "arb":"",
    "ban":"",
    "eng":"17. 'Go to Pharaoh. Indeed, he has transgressed."
  },
  {
    "arb":"",
    "ban":"",
    "eng":"18. And say to him, 'Would you [be willing to] purify yourself"
  },
  {
    "arb":"",
    "ban":"",
    "eng":"19. And let me guide you to your Lord so you would fear [Him]?''"
  },
  {
    "arb":"",
    "ban":"",
    "eng":"20. And he showed him the greatest sign,"
  },
  {
    "arb":"",
    "ban":"",
    "eng":"21. But Pharaoh denied and disobeyed."
  },
  {
    "arb":"",
    "ban":"",
    "eng":"22. Then he turned his back, striving."
  },
  {
    "arb":"",
    "ban":"",
    "eng":"23. And he gathered [his people] and called out"
  },
  {
    "arb":"",
    "ban":"",
    "eng":"24. And said, 'I am your most exalted lord.'"
  },
  {
    "arb":"",
    "ban":"",
    "eng":"25. So Allah seized him in exemplary punishment for the last and the first [transgression]."
  },
  {
    "arb":"",
    "ban":"",
    "eng":"26. Indeed in that is a warning for whoever would fear [Allah]."
  },
  {
    "arb":"",
    "ban":"",
    "eng":"27. Are you a more difficult creation or is the heaven? Allah constructed it."
  },
  {
    "arb":"",
    "ban":"",
    "eng":"28. He raised its ceiling and proportioned it."
  },
  {
    "arb":"",
    "ban":"",
    "eng":"29. And He darkened its night and extracted its brightness."
  },
  {
    "arb":"",
    "ban":"",
    "eng":"30. And after that He spread the earth."
  },
  {
    "arb":"",
    "ban":"",
    "eng":"31. He extracted from it its water and its pasture,"
  },
  {
    "arb":"",
    "ban":"",
    "eng":"32. And the mountains He set firmly"
  },
  {
    "arb":"",
    "ban":"",
    "eng":"33. As provision for you and your grazing livestock."
  },
  {
    "arb":"",
    "ban":"",
    "eng":"34. But when there comes the greatest Overwhelming Calamity -"
  },
  {
    "arb":"",
    "ban":"",
    "eng":"35. The Day when man will remember that for which he strove,"
  },
  {
    "arb":"",
    "ban":"",
    "eng":"36. And Hellfire will be exposed for [all] those who see -"
  },
  {
    "arb":"",
    "ban":"",
    "eng":"37. So as for he who transgressed"
  },
  {
    "arb":"",
    "ban":"",
    "eng":"38. And preferred the life of the world,"
  },
  {
    "arb":"",
    "ban":"",
    "eng":"39. Then indeed, Hellfire will be [his] refuge."
  },
  {
    "arb":"",
    "ban":"",
    "eng":"40. But as for he who feared the position of his Lord and prevented the soul from [unlawful] inclination,"
  },
  {
    "arb":"",
    "ban":"",
    "eng":"41. Then indeed, Paradise will be [his] refuge."
  },
  {
    "arb":"",
    "ban":"",
    "eng":"42. They ask you, [O Muhammad], about the Hour: when is its arrival?"
  },
  {
    "arb":"",
    "ban":"",
    "eng":"43. In what [position] are you that you should mention it?"
  },
  {
    "arb":"",
    "ban":"",
    "eng":"44. To your Lord is its finality."
  },
  {
    "arb":"",
    "ban":"",
    "eng":"45. You are only a warner for those who fear it."
  },
  {
    "arb":"",
    "ban":"",
    "eng":"46. It will be, on the Day they see it, as though they had not remained [in the world] except for an afternoon or a morning thereof."
  }
]
